AutoSite/__init__.py
AutoSite-1.4.dist-info/LICENSE
AutoSite-1.4.dist-info/METADATA
AutoSite-1.4.dist-info/WHEEL
AutoSite-1.4.dist-info/entry_points.txt
AutoSite-1.4.dist-info/top_level.txt
AutoSite-1.4.dist-info/RECORD
