Metadata-Version: 2.1
Name: AutoSite
Version: 1.4
Summary: Keep all your website's pages under one template
Home-page: https://github.com/dotcomboom/AutoSite-Legacy
Author: dotcomboom
Author-email: dotcomboom@somnolescent.net
Classifier: Development Status :: 4 - Beta
Classifier: Environment :: Console
Classifier: Intended Audience :: Developers
Classifier: Intended Audience :: Information Technology
Classifier: Natural Language :: English
Classifier: Programming Language :: Python :: 3
Classifier: License :: Public Domain
Classifier: Operating System :: OS Independent
Classifier: Topic :: Text Processing :: Markup :: HTML
License-File: LICENSE
Requires-Dist: pathlib
Requires-Dist: bs4
Requires-Dist: commonmark
Requires-Dist: argparse
Requires-Dist: dirsync
